odoo/addons/stock_picking_delivery_link/README.rst
odoo/addons/stock_picking_delivery_link/__init__.py
odoo/addons/stock_picking_delivery_link/__manifest__.py
odoo/addons/stock_picking_delivery_link/i18n/stock_picking_delivery_link.pot
odoo/addons/stock_picking_delivery_link/models/__init__.py
odoo/addons/stock_picking_delivery_link/models/stock_picking.py
odoo/addons/stock_picking_delivery_link/readme/CONTRIBUTORS.rst
odoo/addons/stock_picking_delivery_link/readme/DESCRIPTION.rst
odoo/addons/stock_picking_delivery_link/static/description/icon.png
odoo/addons/stock_picking_delivery_link/static/description/index.html
odoo/addons/stock_picking_delivery_link/tests/__init__.py
odoo/addons/stock_picking_delivery_link/tests/common.py
odoo/addons/stock_picking_delivery_link/tests/test_delivery_link.py
odoo/addons/stock_picking_delivery_link/views/stock_picking.xml
odoo13_addon_stock_picking_delivery_link-13.0.1.0.1.dev5.dist-info/METADATA
odoo13_addon_stock_picking_delivery_link-13.0.1.0.1.dev5.dist-info/WHEEL
odoo13_addon_stock_picking_delivery_link-13.0.1.0.1.dev5.dist-info/top_level.txt
odoo13_addon_stock_picking_delivery_link-13.0.1.0.1.dev5.dist-info/RECORD
